markdownwavedrom/__init__.py
markdownwavedrom/plugin.py
mkdocs_wavedrom_plugin-0.1.1.dist-info/LICENSE
mkdocs_wavedrom_plugin-0.1.1.dist-info/METADATA
mkdocs_wavedrom_plugin-0.1.1.dist-info/WHEEL
mkdocs_wavedrom_plugin-0.1.1.dist-info/entry_points.txt
mkdocs_wavedrom_plugin-0.1.1.dist-info/top_level.txt
mkdocs_wavedrom_plugin-0.1.1.dist-info/RECORD
