Metadata-Version: 2.1
Name: mkdocs-wavedrom-plugin
Version: 0.1.1
Summary: A MkDocs plugin for support wavedrom charts in markdown file
Home-page: https://github.com/kuri65536/mkdocs-wavedrom-plugin
Author: Shimoda
Author-email: kuri65536@hotmail.com
License: MPL2
Keywords: mkdocs python markdown wavedrom
Platform: UNKNOWN
Classifier: Development Status :: 3 - Alpha
Classifier: Intended Audience :: Developers
Classifier: Intended Audience :: Information Technology
Classifier: License :: OSI Approved :: Mozilla Public License 2.0 (MPL 2.0)
Classifier: Programming Language :: Python :: 2
Classifier: Programming Language :: Python :: 2.7
Classifier: Programming Language :: Python :: 3
Classifier: Programming Language :: Python :: 3.5
Classifier: Programming Language :: Python :: 3.6
Classifier: Programming Language :: Python :: 3.7
Requires-Python: >=2.7
Requires-Dist: setuptools (>=18.5)
Requires-Dist: beautifulsoup4 (>=4.6.3)
Requires-Dist: mkdocs (>=1.0.4)
Requires-Dist: typing
